Workbook

Sheet Feature Register
A1: Component ID | B1: L1 Domain | C1: Module | D1: Submodule | E1: Function / Workflow | F1: Artifact Type | G1: Arabic / RTL | H1: Priority | I1: Sequence | J1: EGY Market applicability | K1: KSA Market applicability | L1: Recommended Action | M1: Status | N1: Owner | O1: Target Release | P1: Notes | Q1: Current Capability | R1: UI/UX Score (1–5) | S1: Functional Fit (1–5) | T1: Effort (days) | U1: Odoo Equivalent | V1: Odoo Parity | W1: Gap vs Odoo | X1: Code Reference
A2: FIN001 | B2: Financial | C2: GL | D2: Chart of Accounts | E2: Global chart of accounts maintenance | F2: Screen | G2: Partial | H2: High | I2: 1 | M2: Completed | Q2: Create/update GL accounts, classes, types, sub-classes; hierarchical COA with course labels | R2: 3 | S2: 4 | U2: account.account | V2: At Parity | X2: Application/Accounting/GlobalGlSettings/
A3: FIN002 | B3: Financial | C3: GL | D3: Chart of Accounts | E3: GL account hierarchy and sub-class navigation | F3: Screen | G3: Partial | H3: Medium | I3: 2 | M3: Completed | Q3: GetGlAccountHierarchy + GetGlSubClasses drive a true parent/child tree | R3: 3 | S3: 5 | U3: account.group | V3: Ahead | W3: Odoo account groups are a flat prefix convention; this is a real hierarchy | X3: Application/Accounting/OrganizationGlSettings/
A4: FIN003 | B4: Financial | C4: GL | D4: Chart of Accounts | E4: Organization-level COA assignment | F4: Screen | G4: Partial | H4: High | I4: 3 | M4: Completed | Q4: Assign/remove GL accounts per internal organization, bulk property update | R4: 3 | S4: 4 | U4: multi-company COA | V4: At Parity | X4: Application/Accounting/OrganizationGlSettings/AssignGlAccountToOrganization.cs
A5: FIN004 | B5: Financial | C5: GL | D5: Configuration | E5: GL account type defaults | F5: Configuration | G5: Partial | H5: Medium | I5: 4 | M5: Completed | Q5: ListGlAccountTypeDefaults / RemoveGlAccountTypeDefault per organization | R5: 3 | S5: 4 | U5: journal + product category default accounts | V5: At Parity | X5: Application/Accounting/OrganizationGlSettings/
A6: FIN005 | B6: Financial | C6: GL | D6: Configuration | E6: Party / product / category GL overrides | F6: Configuration | G6: Partial | H6: Medium | I6: 5 | M6: Completed | Q6: Per-party, per-product, per-category, per-fin-account-type, per-fixed-asset-type, per-variance-reason GL mapping | R6: 3 | S6: 5 | U6: property fields on partner/product | V6: Ahead | W6: Odoo maps at fewer dimensions out of the box | X6: Application/Accounting/OrganizationGlSettings/
A7: FIN006 | B7: Financial | C7: GL | D7: Journal Entries | E7: Manual accounting transaction entry | F7: Screen | G7: Partial | H7: High | I7: 6 | M7: Completed | Q7: CreateAcctgTrans + CreateAcctgTransEntry, plus QuickCreateAcctgTrans | R7: 3 | S7: 4 | U7: account.move / account.move.line | V7: At Parity | X7: Application/Accounting/Transactions/
A8: FIN007 | B8: Financial | C8: GL | D8: Journal Entries | E8: Post / unpost transactions | F8: Workflow | G8: Partial | H8: High | I8: 7 | M8: Completed | Q8: PostAcctgTrans, UnpostAcctgTrans, CompleteAcctgTransEntries | R8: 3 | S8: 4 | U8: post / reset to draft | V8: At Parity | X8: Application/Accounting/Transactions/PostAcctgTrans.cs
A9: FIN008 | B9: Financial | C9: GL | D9: Journal Entries | E9: Multi-line journal create and update | F9: Screen | G9: Partial | H9: High | I9: 8 | M9: Completed | Q9: CreateMultiAcctgTransWithEntries / UpdateMultiAcctgTransWithEntries | R9: 3 | S9: 4 | U9: account.move form | V9: At Parity | X9: Application/Accounting/Transactions/
A10: FIN009 | B10: Financial | C10: GL | D10: Journal Entries | E10: Duplicate transaction | F10: Screen | G10: Partial | H10: Low | I10: 9 | M10: Completed | Q10: DuplicateAcctgTrans | R10: 3 | S10: 4 | U10: duplicate action | V10: At Parity | X10: Application/Accounting/Transactions/DuplicateAcctgTrans.cs
A11: FIN010 | B11: Financial | C11: GL | D11: Journal Entries | E11: Opening / initial balance transactions | F11: Batch | G11: Partial | H11: Medium | I11: 10 | M11: Completed | Q11: CreateInitialBalanceTrans | R11: 3 | S11: 4 | U11: opening balance wizard | V11: At Parity | X11: Application/Accounting/Transactions/CreateInitialBalanceTrans.cs
A12: FIN011 | B12: Financial | C12: GL | D12: Journal Entries | E12: Transaction listing and drill-down by date range | F12: Screen | G12: Partial | H12: High | I12: 11 | M12: Completed | Q12: ListAccountingTransactions, ...ByDateRange, per-invoice / per-payment / per-work-effort entry views | R12: 3 | S12: 4 | U12: journal items list | V12: At Parity | X12: Application/Accounting/Transactions/
A13: FIN012 | B13: Financial | C13: GL | D13: Period Close | E13: Financial time period close | F13: Workflow | G13: Partial | H13: High | I13: 12 | L13: Add hard lock dates and a re-open audit trail | M13: Completed | Q13: CloseFinancialTimePeriod + custom time period maintenance | R13: 3 | S13: 2 | T13: 10 | U13: fiscal year + lock dates | V13: Behind | W13: Odoo enforces separate journal / tax / all-user lock dates that block posting; close here is advisory | X13: Application/Accounting/OrganizationGlSettings/CloseFinancialTimePeriod.cs
A14: FIN013 | B14: Financial | C14: GL | D14: Reporting | E14: Trial balance report | F14: Report | G14: Partial | H14: High | I14: 13 | M14: Completed | Q14: GetTrialBalanceReport + GetGlAccountTrialBalanceReport | R14: 3 | S14: 4 | U14: Trial Balance | V14: At Parity | X14: Application/Accounting/OrganizationGlSettings/
A15: FIN014 | B15: Financial | C15: GL | D15: Reporting | E15: Balance sheet and comparative balance sheet | F15: Report | G15: Partial | H15: High | I15: 14 | M15: Completed | Q15: GetBalanceSheetReport, GenerateComparativeBalanceSheet, ComparativeBalanceTotal | R15: 3 | S15: 4 | U15: Balance Sheet | V15: At Parity | X15: Application/Accounting/OrganizationGlSettings/
A16: FIN015 | B16: Financial | C16: GL | D16: Reporting | E16: Income statement and comparative | F16: Report | G16: Partial | H16: High | I16: 15 | M16: Completed | Q16: GetIncomeStatementReport + GetComparativeIncomeStatementReport | R16: 3 | S16: 4 | U16: Profit and Loss | V16: At Parity | X16: Application/Accounting/OrganizationGlSettings/
A17: FIN016 | B17: Financial | C17: GL | D17: Reporting | E17: Cash flow statement | F17: Report | G17: Partial | H17: Medium | I17: 16 | M17: Completed | Q17: GetCashFlowStatementReport | R17: 3 | S17: 4 | U17: Cash Flow Statement | V17: At Parity | X17: Application/Accounting/OrganizationGlSettings/GetCashFlowStatementReport.cs
A18: FIN017 | B18: Financial | C18: GL | D18: Reporting | E18: Transaction totals report | F18: Report | G18: Partial | H18: Medium | I18: 17 | M18: Completed | Q18: GetTransactionTotalsReport | R18: 3 | S18: 4 | U18: journal audit report | V18: At Parity | X18: Application/Accounting/OrganizationGlSettings/
A19: FIN018 | B19: Financial | C19: GL | D19: Reporting | E19: Inventory valuation report | F19: Report | G19: Partial | H19: High | I19: 18 | M19: Completed | Q19: GetInventoryValuationReport | R19: 3 | S19: 4 | U19: stock valuation report | V19: At Parity | X19: Application/Accounting/OrganizationGlSettings/GetInventoryValuationReport.cs
A20: FIN019 | B20: Financial | C20: GL | D20: Reporting | E20: GL account transaction detail drill-down | F20: Report | G20: Partial | H20: High | I20: 19 | M20: Completed | Q20: Balance-sheet and income-statement drill-through to underlying entries | R20: 3 | S20: 4 | U20: report drill-down | V20: At Parity | X20: Application/Accounting/OrganizationGlSettings/
A21: FIN020 | B21: Financial | C21: GL | D21: Reporting | E21: Party financial history and sub-ledger | F21: Report | G21: Partial | H21: High | I21: 20 | M21: Completed | Q21: GetPartyFinancialHistory + GetPartySubLedgerDetails | R21: 3 | S21: 4 | U21: Partner Ledger | V21: At Parity | X21: Application/Accounting/Services/
A22: FIN021 | B22: Financial | C22: GL | D22: Reporting | E22: GL account diagram | F22: Screen | G22: Partial | H22: Low | I22: 21 | M22: Completed | Q22: GetGlAccountDiagramQueryHandler renders account relationships visually | R22: 3 | S22: 5 | U22: none | V22: Ahead | W22: No Odoo equivalent | X22: Application/Accounting/Services/GetGlAccountDiagramQueryHandler.cs
A23: FIN022 | B23: Financial | C23: GL | D23: Reporting | E23: Company report | F23: Report | G23: Partial | H23: Medium | I23: 22 | M23: Completed | Q23: GetCompanyReport | R23: 3 | S23: 4 | U23: company overview | V23: At Parity | X23: Application/Accounting/Reports/GetCompanyReport.cs
A24: FIN023 | B24: Financial | C24: GL | D24: Reporting | E24: Aged receivable / payable ageing report | F24: Report | G24: Partial | H24: High | I24: 23 | L24: Build from existing sub-ledger data | M24: Planned | Q24: Partially served by party financial history; no dedicated ageing buckets | R24: 3 | S24: 2 | T24: 8 | U24: Aged Receivable / Aged Payable | V24: Behind | W24: Odoo ships bucketed ageing with drill-down and PDF/XLSX export
A25: FIN024 | B25: Financial | C25: GL | D25: Reporting | E25: Budget vs actual | F25: Report | G25: Not Applicable | H25: Medium | I25: 24 | L25: Track E dependency - needs a charting layer first | M25: Planned | Q25: No budgeting entity or report | S25: 1 | T25: 20 | U25: account_budget | V25: Gap - not built | W25: Referenced as FIN-BUD in the ERPv2 five-track plan
A26: FIN025 | B26: Financial | C26: AR | D26: Invoice Processing | E26: Sales invoice entry | F26: Screen | G26: Partial | H26: High | I26: 25 | M26: Completed | Q26: CreateInvoice, CreateInvoiceItem, UpdateInvoice, UpdateInvoiceItem | R26: 3 | S26: 4 | U26: account.move (out_invoice) | V26: At Parity | X26: Application/Accounting/Invoices/
A27: FIN026 | B27: Financial | C27: AP | D27: Invoice Processing | E27: Purchase invoice entry | F27: Screen | G27: Partial | H27: High | I27: 26 | M27: Completed | Q27: Same handler set driven by invoice type | R27: 3 | S27: 4 | U27: account.move (in_invoice) | V27: At Parity | X27: Application/Accounting/Invoices/
A28: FIN027 | B28: Financial | C28: AR | D28: Invoice Processing | E28: Invoice item maintenance | F28: Screen | G28: Partial | H28: High | I28: 27 | M28: Completed | Q28: CreateInvoiceItem / UpdateInvoiceItem / DeleteInvoiceItem | R28: 3 | S28: 4 | U28: invoice lines | V28: At Parity | X28: Application/Accounting/Invoices/
A29: FIN028 | B29: Financial | C29: AR | D29: Invoice Processing | E29: Invoice status workflow | F29: Workflow | G29: Partial | H29: High | I29: 28 | M29: Completed | Q29: ChangeInvoiceStatus + ResetInvoice | R29: 3 | S29: 4 | U29: draft / posted / cancel | V29: At Parity | X29: Application/Accounting/Invoices/ChangeInvoiceStatus.cs
A30: FIN029 | B30: Financial | C30: AR | D30: Invoice Processing | E30: Invoice total calculation | F30: API | G30: Partial | H30: High | I30: 29 | M30: Completed | Q30: CalculateInvoiceTotal | R30: 3 | S30: 4 | U30: computed totals | V30: At Parity | X30: Application/Accounting/Invoices/CalculateInvoiceTotal.cs
A31: FIN030 | B31: Financial | C31: AR | D31: Invoice Processing | E31: Invoice listing and search | F31: Screen | G31: Partial | H31: High | I31: 30 | M31: Completed | Q31: ListInvoices, ListInvoice, ListNotAppliedInvoices | R31: 3 | S31: 4 | U31: invoice list views | V31: At Parity | X31: Application/Accounting/Invoices/
A32: FIN031 | B32: Financial | C32: AR | D32: Invoice Processing | E32: Invoice generation from shipments | F32: Batch | G32: Partial | H32: Medium | I32: 31 | M32: Completed | Q32: CreateInvoicesFromShipments | R32: 3 | S32: 4 | U32: invoice from delivery | V32: At Parity | X32: Application/Accounting/Invoices/
A33: FIN032 | B33: Financial | C33: AP | D33: Payroll | E33: Payroll invoice batch creation | F33: Batch | G33: Partial | H33: High | I33: 32 | M33: Completed | Q33: BatchCreatePayrollInvoices, CheckExistingPayrollInvoices, DeletePayrollInvoices, ListPayrollData2 | R33: 3 | S33: 5 | U33: hr_payroll (separate app) | V33: Ahead | W33: Payroll posts straight to AP invoices here; net is rounded per invoice to 2dp then summed | X33: Application/Accounting/Invoices/BatchCreatePayrollInvoices.cs
A34: FIN033 | B34: Financial | C34: AP | D34: Invoice Processing | E34: Supply certificate accounting remediation | F34: Batch | G34: Partial | H34: Low | I34: 33 | M34: Completed | Q34: RemediateSupplyCertificateAccounting + RemediateSupplyCertificateDuplicateAp | R34: 3 | S34: 5 | U34: none | V34: Ahead | W34: Data-repair tooling for a project-specific posting defect | X34: Application/Accounting/Invoices/
A35: FIN034 | B35: Financial | C35: AR | D35: Compliance | E35: e-Invoicing - ZATCA (KSA) | F35: API | G35: Not Applicable | H35: High | I35: 34 | J35: Not Applicable | K35: Non-Compliant | L35: Required before any KSA deployment | M35: Planned | Q35: Nothing built | S35: 1 | T35: 45 | U35: l10n_sa_edi | V35: Gap - not built | W35: Phase 2 ZATCA clearance, XML/UBL, QR, CSID onboarding all absent
A36: FIN035 | B36: Financial | C36: AR | D36: Compliance | E36: e-Invoicing - Egypt ETA | F36: API | G36: Not Applicable | H36: High | I36: 35 | J36: Non-Compliant | K36: Not Applicable | L36: Required for the EGY market | M36: Planned | Q36: Nothing built | S36: 1 | T36: 35 | U36: l10n_eg_edi_eta | V36: Gap - not built | W36: ETA JSON submission, UUID, signing all absent
A37: FIN036 | B37: Financial | C37: AR | D37: Payment Processing | E37: Incoming payment entry | F37: Screen | G37: Partial | H37: High | I37: 36 | M37: Completed | Q37: CreatePayment + ListIncomingPayments + ListIncomingPaymentTypes | R37: 3 | S37: 4 | U37: account.payment (inbound) | V37: At Parity | X37: Application/Accounting/Payments/
A38: FIN037 | B38: Financial | C38: AP | D38: Payment Processing | E38: Outgoing payment entry | F38: Screen | G38: Partial | H38: High | I38: 37 | M38: Completed | Q38: CreatePayment + ListOutgoingPayments + ListOutgoingPaymentTypes | R38: 3 | S38: 4 | U38: account.payment (outbound) | V38: At Parity | X38: Application/Accounting/Payments/
A39: FIN038 | B39: Financial | C39: AR | D39: Payment Processing | E39: Payment application to invoices | F39: Screen | G39: Partial | H39: High | I39: 38 | M39: Completed | Q39: CreatePaymentApplication, RemovePaymentApplication, ListPaymentsApplicationsForInvoice | R39: 3 | S39: 4 | U39: payment matching | V39: At Parity | X39: Application/Accounting/Payments/
A40: FIN039 | B40: Financial | C40: AR | D40: Payment Processing | E40: Combined payment and application | F40: API | G40: Partial | H40: Medium | I40: 39 | M40: Completed | Q40: CreatePaymentAndApplication + CreatePaymentAndFinAccountTrans | R40: 3 | S40: 4 | U40: register payment wizard | V40: At Parity | X40: Application/Accounting/Payments/
A41: FIN040 | B41: Financial | C41: AR | D41: Payment Processing | E41: Payment status workflow | F41: Workflow | G41: Partial | H41: High | I41: 40 | M41: Completed | Q41: SetPaymentStatusToReceived, ResetPayment, UpdateOrApproveOrderPayments | R41: 3 | S41: 4 | U41: payment state machine | V41: At Parity | X41: Application/Accounting/Payments/
A42: FIN041 | B42: Financial | C42: AP | D42: Payment Processing | E42: Payment groups and check runs | F42: Batch | G42: Partial | H42: Medium | I42: 41 | M42: Completed | Q42: CreatePaymentGroup, CreatePaymentGroupPayment, CancelCheckRun, ExpirePaymentGroupMember | R42: 3 | S42: 4 | U42: batch payments | V42: At Parity | X42: Application/Accounting/PaymentGroup/
A43: FIN042 | B43: Financial | C43: AP | D43: Payment Processing | E43: Payment methods per party | F43: Configuration | G43: Partial | H43: Medium | I43: 42 | M43: Completed | Q43: ListPaymentMethods, ListPaymentMethodsByPartyId, payment method types | R43: 3 | S43: 4 | U43: partner bank / payment method | V43: At Parity | X43: Application/Accounting/Payments/
A44: FIN043 | B44: Financial | C44: AR | D44: Payment Processing | E44: Payment report PDF | F44: Report | G44: Partial | H44: Medium | I44: 43 | M44: Completed | Q44: GeneratePaymentReportPdf | R44: 3 | S44: 4 | U44: payment receipt report | V44: At Parity | X44: Application/Accounting/Payments/GeneratePaymentReportPdf.cs
A45: FIN044 | B45: Financial | C45: AR | D45: Payment Processing | E45: Payments due status tracking | F45: Screen | G45: Partial | H45: Medium | I45: 44 | M45: Completed | Q45: ListPaymentsWithDueStatus + ...ByDateRange, ListPaymentsToday | R45: 3 | S45: 4 | U45: follow-up reports | V45: At Parity | X45: Application/Accounting/Payments/
A46: FIN045 | B46: Financial | C46: AR | D46: Payment Processing | E46: Offline payment receipt | F46: Screen | G46: Partial | H46: Medium | I46: 45 | M46: Completed | Q46: ReceiveOfflinePayment | R46: 3 | S46: 4 | U46: manual payment | V46: At Parity | X46: Application/Order/Orders/ReceiveOfflinePayment.cs
A47: FIN046 | B47: Financial | C47: AR | D47: Payment Processing | E47: Installment payment accounting | F47: Workflow | G47: Partial | H47: High | I47: 46 | M47: Completed | Q47: RecordInstallmentPaymentAccounting for real-estate installment sales | R47: 3 | S47: 5 | U47: none | V47: Ahead | W47: No Odoo equivalent for installment-sale revenue handling | X47: Application/Accounting/Payments/RecordInstallmentPaymentAccounting.cs
A48: FIN047 | B48: Financial | C48: AR | D48: Payment Processing | E48: Cheque recording | F48: Screen | G48: Partial | H48: High | I48: 47 | M48: Completed | Q48: RecordSalesRequestCheques + ListChequeableSalesRequestPayments | R48: 3 | S48: 5 | U48: check printing only | V48: Ahead | W48: Odoo handles check printing, not post-dated cheque registers | X48: Application/Order/SalesRequests/RecordSalesRequestCheques.cs
A49: FIN048 | B49: Financial | C49: AR | D49: Payment Processing | E49: Bank reconciliation | F49: Screen | G49: Not Applicable | H49: High | I49: 48 | L49: Highest-value accounting gap vs Odoo | M49: Planned | Q49: FinAccount transactions exist but there is no statement import or matching UI | S49: 1 | T49: 30 | U49: account_reconcile + bank statement import | V49: Gap - not built | W49: Odoo imports OFX/QIF/CSV/CAMT and offers a reconciliation widget with matching rules
A50: FIN049 | B50: Financial | C50: AR | D50: Payment Processing | E50: Online payment providers | F50: API | G50: Not Applicable | H50: Low | I50: 49 | M50: Planned | Q50: Nothing built | S50: 1 | T50: 20 | U50: payment providers (Stripe, Paypal, ...) | V50: Gap - not built | W50: No card or gateway capture path
A51: FIN050 | B51: Financial | C51: Treasury | D51: Financial Accounts | E51: Financial account register | F51: Screen | G51: Partial | H51: High | I51: 50 | M51: Completed | Q51: ListFinAccounts + ListFinAccountsForParty | R51: 3 | S51: 4 | U51: journals / bank accounts | V51: At Parity | X51: Application/Accounting/FinAccounts/
A52: FIN051 | B52: Financial | C52: Treasury | D52: Financial Accounts | E52: Deposits and withdrawals | F52: Screen | G52: Partial | H52: High | I52: 51 | M52: Completed | Q52: DepositWithdrawPayments + GetDepositWithdrawPayments | R52: 3 | S52: 4 | U52: bank statement lines | V52: At Parity | X52: Application/Accounting/FinAccounts/DepositWithdrawPayments.cs
A53: FIN052 | B53: Financial | C53: Treasury | D53: Financial Accounts | E53: FinAccount transactions and totals | F53: Screen | G53: Partial | H53: Medium | I53: 52 | M53: Completed | Q53: GetFinAccountTransListAndTotals, status and type LOVs | R53: 3 | S53: 4 | U53: journal items | V53: At Parity | X53: Application/Accounting/FinAccounts/
A54: FIN053 | B54: Financial | C54: Treasury | D54: Financial Accounts | E54: Post FinAccount transactions to GL | F54: Workflow | G54: Partial | H54: High | I54: 53 | M54: Completed | Q54: PostFinAccountTransToGl | R54: 3 | S54: 4 | U54: automatic journal posting | V54: At Parity | X54: Application/Accounting/FinAccounts/
A55: FIN054 | B55: Financial | C55: AR | D55: Billing Accounts | E55: Billing account maintenance | F55: Screen | G55: Partial | H55: Medium | I55: 54 | M55: Completed | Q55: createBillingAccount + UpdateBillingAccount | R55: 3 | S55: 5 | U55: credit limit on partner | V55: Ahead | W55: Odoo has no billing-account concept; credit is a partner field | X55: Application/Accounting/BillingAccounts/
A56: FIN055 | B56: Financial | C56: AR | D56: Billing Accounts | E56: Billing account balance | F56: Report | G56: Partial | H56: Medium | I56: 55 | M56: Completed | Q56: GetBillingAccountBalance + GetBalancesForVendorAndProject | R56: 3 | S56: 4 | U56: partner balance | V56: At Parity | X56: Application/Accounting/BillingAccounts/
A57: FIN056 | B57: Financial | C57: AR | D57: Billing Accounts | E57: Billing account invoices, payments and orders | F57: Screen | G57: Partial | H57: Medium | I57: 56 | M57: Completed | Q57: ListBillingAccountInvoices, GetBillingAccountPayments, GetBillingAccountOrders | R57: 3 | S57: 4 | U57: partner related documents | V57: At Parity | X57: Application/Accounting/BillingAccounts/
A58: FIN057 | B58: Financial | C58: Tax | D58: Tax Setup | E58: Tax authority configuration | F58: Configuration | G58: Partial | H58: High | I58: 57 | M58: Completed | Q58: ListTaxAuthorities, GetTaxAuthorityCategories, GetTaxAuthorityGlAccounts | R58: 3 | S58: 2 | U58: account.tax + fiscal positions | V58: Behind | W58: Odoo fiscal positions remap taxes and accounts per partner; no equivalent here | X58: Application/Accounting/Taxes/
A59: FIN058 | B59: Financial | C59: Tax | D59: Tax Calculation | E59: Tax calculation on sales orders | F59: API | G59: Partial | H59: High | I59: 58 | M59: Completed | Q59: CalculateTaxAdjustmentsForSalesOrder + CalculateTax | R59: 3 | S59: 4 | U59: tax engine on order lines | V59: At Parity | X59: Application/Accounting/Taxes/
A60: FIN059 | B60: Financial | C60: Tax | D60: Tax Calculation | E60: Tax calculation on quotes | F60: API | G60: Partial | H60: Medium | I60: 59 | M60: Completed | Q60: CalculateTaxAdjustmentsForQuote | R60: 3 | S60: 4 | U60: tax engine on quotations | V60: At Parity | X60: Application/Accounting/Taxes/CalculateTaxAdjustmentsForQuote.cs
A61: FIN060 | B61: Financial | C61: Tax | D61: Tax Setup | E61: Tax authority rate products | F61: Configuration | G61: Partial | H61: Medium | I61: 60 | M61: Completed | Q61: GetTaxAuthorityRateProducts | R61: 3 | S61: 4 | U61: tax per product | V61: At Parity | X61: Application/Accounting/Taxes/
A62: FIN061 | B62: Financial | C62: Tax | D62: Tax Reporting | E62: VAT return / tax report | F62: Report | G62: Not Applicable | H62: High | I62: 61 | J62: Non-Compliant | K62: Non-Compliant | L62: Needed for both EGY and KSA filing | M62: Planned | Q62: Tax amounts are calculated and posted but never aggregated into a filing view | S62: 1 | T62: 15 | U62: Tax Report (per country localization) | V62: Gap - not built
A63: FIN062 | B63: Financial | C63: Assets | D63: Fixed Assets | E63: Fixed asset register | F63: Screen | G63: Partial | H63: Medium | I63: 62 | M63: Completed | Q63: ListFixedAssets + fixed asset types | R63: 3 | S63: 2 | U63: account.asset | V63: Behind | W63: Register exists but is largely static | X63: Application/Accounting/FixedAssets/
A64: FIN063 | B64: Financial | C64: Assets | D64: Fixed Assets | E64: Fixed asset standard costs | F64: Screen | G64: Partial | H64: Medium | I64: 63 | M64: Completed | Q64: ListFixedAssetStdCosts + ListFixedAssetStdCostTypes | R64: 3 | S64: 4 | U64: asset cost | V64: At Parity | X64: Application/Accounting/FixedAssets/
A65: FIN064 | B65: Financial | C65: Assets | D65: Fixed Assets | E65: Depreciation schedules and runs | F65: Batch | G65: Not Applicable | H65: High | I65: 64 | M65: Planned | Q65: No depreciation calculation or posting anywhere | S65: 1 | T65: 20 | U65: account_asset depreciation board | V65: Gap - not built | W65: Odoo generates the depreciation board and posts entries automatically
A66: FIN065 | B66: Financial | C66: Costing | D66: Cost Centers | E66: Cost center maintenance | F66: Screen | G66: Partial | H66: Medium | I66: 65 | L66: Compare against Odoo analytic distribution before extending | M66: Completed | Q66: CreateCostCenter + GetCostCenters | R66: 3 | S66: 2 | T66: 12 | U66: account.analytic.account | V66: Behind | W66: Odoo supports multi-dimensional analytic distribution with percentage splits per line | X66: Application/Accounting/CostCenters/
A67: FIN066 | B67: Financial | C67: Costing | D67: Product Costing | E67: Product cost components | F67: Screen | G67: Partial | H67: High | I67: 66 | M67: Completed | Q67: GetProductCostComponets + GetActualProductCostComponents | R67: 3 | S67: 5 | U67: product standard price | V67: Ahead | W67: Component-level costing is richer than Odoo standard/AVCO/FIFO | X67: Application/Accounting/Costs/
A68: FIN067 | B68: Financial | C68: Costing | D68: Product Costing | E68: Cost component calculations | F68: Configuration | G68: Partial | H68: Medium | I68: 67 | M68: Completed | Q68: GetProductCostComponetCalcs + ListCostComponentCalcs | R68: 3 | S68: 5 | U68: no equivalent | V68: Ahead | X68: Application/Accounting/Costs/
A69: FIN068 | B69: Financial | C69: Costing | D69: Product Costing | E69: Material cost configuration | F69: Configuration | G69: Partial | H69: Medium | I69: 68 | M69: Completed | Q69: GetMaterialCostConfig | R69: 3 | S69: 4 | U69: costing method on category | V69: At Parity | X69: Application/Accounting/Costs/GetMaterialCostConfig.cs
A70: FIN069 | B70: Financial | C70: Costing | D70: Product Costing | E70: Routing task and fixed asset costs | F70: Configuration | G70: Partial | H70: Medium | I70: 69 | M70: Completed | Q70: GetRoutingTaskCostComponentCalcs + GetRoutingTaskFixedAssetCosts | R70: 3 | S70: 5 | U70: workcenter cost/hour | V70: Ahead | X70: Application/Accounting/Costs/
A71: FIN070 | B71: Financial | C71: Contracts | D71: Agreements | E71: Agreement register | F71: Screen | G71: Partial | H71: Medium | I71: 70 | M71: Completed | Q71: ListAgreements + GetAgreementsByPartyId + agreement types | R71: 3 | S71: 2 | U71: contracts (sale_subscription) | V71: Behind | W71: No recurring billing or renewal automation | X71: Application/Accounting/Agreement/
A72: FIN071 | B72: Financial | C72: Contracts | D72: Agreements | E72: Agreement items and terms | F72: Screen | G72: Partial | H72: Medium | I72: 71 | M72: Completed | Q72: GetAgreementItems + GetAgreementTerms | R72: 3 | S72: 4 | U72: contract lines | V72: At Parity | X72: Application/Accounting/Agreement/
A73: FIN072 | B73: Financial | C73: GL | D73: Multi-currency | E73: Foreign exchange rates | F73: Configuration | G73: Partial | H73: Medium | I73: 72 | L73: Add scheduled rate refresh | M73: Completed | Q73: ListForeignExchangeRates over dated UOM conversions | R73: 3 | S73: 2 | T73: 5 | U73: res.currency.rate + auto-update | V73: Behind | W73: Odoo pulls rates from ECB/other providers on a schedule; rates are manual here | X73: Application/Accounting/ForeignExchangeRates/
A74: ORD001 | B74: Order Management | C74: Sales Orders | D74: Order Entry | E74: Sales order entry | F74: Screen | G74: Partial | H74: High | I74: 1 | M74: Completed | Q74: CreateSalesOrder with items, adjustments, ship groups, payment preferences | R74: 3 | S74: 4 | U74: sale.order | V74: At Parity | X74: Application/Order/Orders/Orders/CreateSalesOrder.cs
A75: ORD002 | B75: Order Management | C75: Sales Orders | D75: Order Entry | E75: Sales order item maintenance | F75: Screen | G75: Partial | H75: High | I75: 2 | M75: Completed | Q75: UpdateOrApproveSalesOrderItems, GetSalesOrderItemProduct | R75: 3 | S75: 4 | U75: sale.order.line | V75: At Parity | X75: Application/Order/Orders/Orders/
A76: ORD003 | B76: Order Management | C76: Sales Orders | D76: Order Entry | E76: Sales order adjustments | F76: Screen | G76: Partial | H76: High | I76: 3 | M76: Completed | Q76: CreateSalesOrderAdjustments, ListSalesOrderAdjustments, adjustment types | R76: 3 | S76: 4 | U76: discounts / charges on lines | V76: At Parity | X76: Application/Order/Orders/Orders/
A77: ORD004 | B77: Order Management | C77: Sales Orders | D77: Approval | E77: Sales order approval workflow | F77: Workflow | G77: Partial | H77: High | I77: 4 | M77: Completed | Q77: UpdateOrApproveSalesOrder drives the status transition | R77: 3 | S77: 4 | U77: confirm / lock / cancel | V77: At Parity | X77: Application/Order/Orders/Orders/UpdateOrApproveSalesOrder.cs
A78: ORD005 | B78: Order Management | C78: Sales Orders | D78: Order Entry | E78: Sales order listing and search | F78: Screen | G78: Partial | H78: High | I78: 5 | M78: Completed | Q78: ListSalesOrder, ListOrders, ListSalesOrdersByPartyId, OData OrderRecords | R78: 3 | S78: 4 | U78: sale.order list | V78: At Parity | X78: Application/Order/Orders/Orders/
A79: ORD006 | B79: Order Management | C79: Sales Orders | D79: Order Entry | E79: Order summary and totals | F79: Screen | G79: Partial | H79: Medium | I79: 6 | M79: Completed | Q79: GetOrderSummary + OrderReadHelper + TotalsInfo | R79: 3 | S79: 4 | U79: order totals | V79: At Parity | X79: Application/Order/Orders/Orders/GetOrderSummary.cs
A80: ORD007 | B80: Order Management | C80: Sales Orders | D80: Order Entry | E80: Order terms | F80: Screen | G80: Partial | H80: Medium | I80: 7 | M80: Completed | Q80: GetOrderTerms + ListTermTypesLov | R80: 3 | S80: 4 | U80: payment terms | V80: At Parity | X80: Application/Order/Orders/Orders/GetOrderTerms.cs
A81: ORD008 | B81: Order Management | C81: Sales Orders | D81: Fulfilment | E81: Quick ship sales order | F81: Workflow | G81: Partial | H81: Medium | I81: 8 | M81: Completed | Q81: QuickShipSalesOrder ships in one action | R81: 3 | S81: 4 | U81: deliver in one step | V81: At Parity | X81: Application/Order/Orders/Orders/QuickShipSalesOrder.cs
A82: ORD009 | B82: Order Management | C82: Sales Orders | D82: Payment | E82: Order payment preferences | F82: Screen | G82: Partial | H82: High | I82: 9 | M82: Completed | Q82: GetSalesOrderPaymentPreference, CartPaymentInfo, OrderPaymentInfoInput | R82: 3 | S82: 4 | U82: payment terms / provider | V82: At Parity | X82: Application/Order/Orders/Orders/
A83: ORD010 | B83: Order Management | C83: Sales Orders | D83: Payment | E83: Complete sales order payments | F83: Workflow | G83: Partial | H83: High | I83: 10 | M83: Completed | Q83: CompleteSalesOrderPayments + CreatePaymentFromOrder | R83: 3 | S83: 4 | U83: register payment on order | V83: At Parity | X83: Application/Accounting/Payments/CompleteSalesOrderPayments.cs
A84: ORD011 | B84: Order Management | C84: Sales Orders | D84: Fulfilment | E84: Back-ordered quantity tracking | F84: API | G84: Partial | H84: Medium | I84: 11 | M84: Completed | Q84: GetItemBackOrderedQuantity + CheckItemStatusOutput | R84: 3 | S84: 2 | U84: backorder handling | V84: Behind | W84: Odoo creates and tracks backorder pickings as first-class records | X84: Application/Order/Orders/Orders/
A85: ORD012 | B85: Order Management | C85: Sales Orders | D85: Order Entry | E85: Orders by party | F85: Screen | G85: Partial | H85: Medium | I85: 12 | M85: Completed | Q85: GetPartyOrders | R85: 3 | S85: 4 | U85: partner order history | V85: At Parity | X85: Application/Order/Orders/Orders/GetPartyOrders.cs
A86: ORD013 | B86: Order Management | C86: Returns | D86: RMA | E86: Return authorization header | F86: Screen | G86: Partial | H86: Medium | I86: 13 | M86: Completed | Q86: CreateReturnHeader + GetReturnById | R86: 3 | S86: 4 | U86: stock.return.picking | V86: At Parity | X86: Application/Order/Orders/Returns/
A87: ORD014 | B87: Order Management | C87: Returns | D87: RMA | E87: Returnable item determination | F87: API | G87: Partial | H87: Medium | I87: 14 | M87: Completed | Q87: GetReturnableItems + ItemReturnedQuantity + ReturnableItemInfo | R87: 3 | S87: 4 | U87: return wizard | V87: At Parity | X87: Application/Order/Orders/Returns/
A88: ORD015 | B88: Order Management | C88: Returns | D88: RMA | E88: Return item processing and adjustments | F88: Workflow | G88: Partial | H88: Medium | I88: 15 | M88: Completed | Q88: ProcessReturnItemsOrAdjustments | R88: 3 | S88: 4 | U88: return + credit note | V88: At Parity | X88: Application/Order/Orders/Returns/
A89: ORD016 | B89: Order Management | C89: Returns | D89: RMA | E89: Return listing and status | F89: Screen | G89: Partial | H89: Medium | I89: 16 | M89: Completed | Q89: ListReturns, ListReturnItems, status LOVs | R89: 3 | S89: 4 | U89: return list | V89: At Parity | X89: Application/Order/Orders/Returns/
A90: ORD017 | B90: Order Management | C90: Quotes | D90: Quotation | E90: Quote entry | F90: Screen | G90: Partial | H90: High | I90: 17 | M90: Completed | Q90: CreateQuote with items and adjustments | R90: 3 | S90: 4 | U90: sale.order (draft quotation) | V90: At Parity | X90: Application/Order/Quotes/CreateQuote.cs
A91: ORD018 | B91: Order Management | C91: Quotes | D91: Quotation | E91: Quote items | F91: Screen | G91: Partial | H91: High | I91: 18 | M91: Completed | Q91: ListQuoteItems + GetQuoteItemProduct | R91: 3 | S91: 4 | U91: quotation lines | V91: At Parity | X91: Application/Order/Quotes/
A92: ORD019 | B92: Order Management | C92: Quotes | D92: Quotation | E92: Quote adjustments | F92: Screen | G92: Partial | H92: Medium | I92: 19 | M92: Completed | Q92: ListQuoteAdjustments + quote adjustment types | R92: 3 | S92: 4 | U92: quotation discounts | V92: At Parity | X92: Application/Order/Quotes/
A93: ORD020 | B93: Order Management | C93: Quotes | D93: Approval | E93: Quote approval | F93: Workflow | G93: Partial | H93: High | I93: 20 | M93: Completed | Q93: UpdateOrApproveQuote | R93: 3 | S93: 4 | U93: confirm quotation | V93: At Parity | X93: Application/Order/Quotes/UpdateOrApproveQuote.cs
A94: ORD021 | B94: Order Management | C94: Quotes | D94: Conversion | E94: Quote to job order conversion | F94: Workflow | G94: Partial | H94: High | I94: 21 | M94: Completed | Q94: CreateJobOrderFromQuote | R94: 3 | S94: 5 | U94: quotation to sale order | V94: Ahead | W94: Job orders are a distinct construction-oriented document type Odoo lacks | X94: Application/Order/JobOrders/CreateJobOrderFromQuote.cs
A95: ORD022 | B95: Order Management | C95: Quotes | D95: Quotation | E95: Online quote portal and e-signature | F95: Screen | G95: Not Applicable | H95: Low | I95: 22 | M95: Planned | Q95: Nothing built | S95: 1 | T95: 18 | U95: sale portal + sign | V95: Gap - not built | W95: Odoo lets customers view, comment on and sign quotations online
A96: ORD023 | B96: Order Management | C96: Job Orders | D96: Job Orders | E96: Job order register | F96: Screen | G96: Partial | H96: High | I96: 23 | M96: Completed | Q96: ListJobOrders + job order items and adjustments | R96: 3 | S96: 5 | U96: none | V96: Ahead | X96: Application/Order/JobOrders/
A97: ORD024 | B97: Order Management | C97: Customer Requests | D97: Requests | E97: Customer request listing | F97: Screen | G97: Partial | H97: Medium | I97: 24 | M97: Completed | Q97: ListCustomerRequests + customer request types | R97: 3 | S97: 2 | U97: helpdesk.ticket | V97: Behind | W97: No SLA, stages, assignment or customer-facing ticket portal | X97: Application/Order/CustomerRequests/
A98: ORD025 | B98: Order Management | C98: Sales Requests | D98: Real Estate | E98: Sales request register | F98: Screen | G98: Partial | H98: High | I98: 25 | M98: Completed | Q98: ListSalesRequestsQuery + by-date-range variants | R98: 3 | S98: 5 | U98: none | V98: Ahead | W98: Real-estate installment-sales workflow; no Odoo counterpart | X98: Application/Order/SalesRequests/
A99: ORD026 | B99: Order Management | C99: Sales Requests | D99: Real Estate | E99: Installment price calculation | F99: API | G99: Partial | H99: High | I99: 26 | M99: Completed | Q99: CalculateInstallmentPrice | R99: 3 | S99: 5 | U99: none | V99: Ahead | X99: Application/Order/SalesRequests/CalculateInstallmentPrice.cs
A100: ORD027 | B100: Order Management | C100: Sales Requests | D100: Real Estate | E100: Installment schedule | F100: Screen | G100: Partial | H100: High | I100: 27 | M100: Completed | Q100: GetInstallmentsQuery | R100: 3 | S100: 5 | U100: none | V100: Ahead | X100: Application/Order/SalesRequests/GetInstallmentsQuery.cs
...

Sheet Odoo Gap Summary
A1: Coverage rollup — Contracts ERP vs Odoo
A3: L1 Domain | B3: Ahead | C3: At Parity | D3: Behind | E3: Gap - not built | F3: Total | G3: Build days
A4: Financial | B4: =COUNTIFS('Feature Register'!$B:$B,$A4,'Feature Register'!$V:$V,B$3) | C4: =COUNTIFS('Feature Register'!$B:$B,$A4,'Feature Register'!$V:$V,C$3) | D4: =COUNTIFS('Feature Register'!$B:$B,$A4,'Feature Register'!$V:$V,D$3) | E4: =COUNTIFS('Feature Register'!$B:$B,$A4,'Feature Register'!$V:$V,E$3) | F4: =SUM(B4:E4) | G4: =SUMIF('Feature Register'!$B:$B,$A4,'Feature Register'!$T:$T)
A5: Order Management | B5: =COUNTIFS('Feature Register'!$B:$B,$A5,'Feature Register'!$V:$V,B$3) | C5: =COUNTIFS('Feature Register'!$B:$B,$A5,'Feature Register'!$V:$V,C$3) | D5: =COUNTIFS('Feature Register'!$B:$B,$A5,'Feature Register'!$V:$V,D$3) | E5: =COUNTIFS('Feature Register'!$B:$B,$A5,'Feature Register'!$V:$V,E$3) | F5: =SUM(B5:E5) | G5: =SUMIF('Feature Register'!$B:$B,$A5,'Feature Register'!$T:$T)
A6: Procurement | B6: =COUNTIFS('Feature Register'!$B:$B,$A6,'Feature Register'!$V:$V,B$3) | C6: =COUNTIFS('Feature Register'!$B:$B,$A6,'Feature Register'!$V:$V,C$3) | D6: =COUNTIFS('Feature Register'!$B:$B,$A6,'Feature Register'!$V:$V,D$3) | E6: =COUNTIFS('Feature Register'!$B:$B,$A6,'Feature Register'!$V:$V,E$3) | F6: =SUM(B6:E6) | G6: =SUMIF('Feature Register'!$B:$B,$A6,'Feature Register'!$T:$T)
A7: Inventory | B7: =COUNTIFS('Feature Register'!$B:$B,$A7,'Feature Register'!$V:$V,B$3) | C7: =COUNTIFS('Feature Register'!$B:$B,$A7,'Feature Register'!$V:$V,C$3) | D7: =COUNTIFS('Feature Register'!$B:$B,$A7,'Feature Register'!$V:$V,D$3) | E7: =COUNTIFS('Feature Register'!$B:$B,$A7,'Feature Register'!$V:$V,E$3) | F7: =SUM(B7:E7) | G7: =SUMIF('Feature Register'!$B:$B,$A7,'Feature Register'!$T:$T)
A8: Logistics | B8: =COUNTIFS('Feature Register'!$B:$B,$A8,'Feature Register'!$V:$V,B$3) | C8: =COUNTIFS('Feature Register'!$B:$B,$A8,'Feature Register'!$V:$V,C$3) | D8: =COUNTIFS('Feature Register'!$B:$B,$A8,'Feature Register'!$V:$V,D$3) | E8: =COUNTIFS('Feature Register'!$B:$B,$A8,'Feature Register'!$V:$V,E$3) | F8: =SUM(B8:E8) | G8: =SUMIF('Feature Register'!$B:$B,$A8,'Feature Register'!$T:$T)
A9: Manufacturing | B9: =COUNTIFS('Feature Register'!$B:$B,$A9,'Feature Register'!$V:$V,B$3) | C9: =COUNTIFS('Feature Register'!$B:$B,$A9,'Feature Register'!$V:$V,C$3) | D9: =COUNTIFS('Feature Register'!$B:$B,$A9,'Feature Register'!$V:$V,D$3) | E9: =COUNTIFS('Feature Register'!$B:$B,$A9,'Feature Register'!$V:$V,E$3) | F9: =SUM(B9:E9) | G9: =SUMIF('Feature Register'!$B:$B,$A9,'Feature Register'!$T:$T)
A10: Projects | B10: =COUNTIFS('Feature Register'!$B:$B,$A10,'Feature Register'!$V:$V,B$3) | C10: =COUNTIFS('Feature Register'!$B:$B,$A10,'Feature Register'!$V:$V,C$3) | D10: =COUNTIFS('Feature Register'!$B:$B,$A10,'Feature Register'!$V:$V,D$3) | E10: =COUNTIFS('Feature Register'!$B:$B,$A10,'Feature Register'!$V:$V,E$3) | F10: =SUM(B10:E10) | G10: =SUMIF('Feature Register'!$B:$B,$A10,'Feature Register'!$T:$T)
A11: Catalog | B11: =COUNTIFS('Feature Register'!$B:$B,$A11,'Feature Register'!$V:$V,B$3) | C11: =COUNTIFS('Feature Register'!$B:$B,$A11,'Feature Register'!$V:$V,C$3) | D11: =COUNTIFS('Feature Register'!$B:$B,$A11,'Feature Register'!$V:$V,D$3) | E11: =COUNTIFS('Feature Register'!$B:$B,$A11,'Feature Register'!$V:$V,E$3) | F11: =SUM(B11:E11) | G11: =SUMIF('Feature Register'!$B:$B,$A11,'Feature Register'!$T:$T)
A12: Parties | B12: =COUNTIFS('Feature Register'!$B:$B,$A12,'Feature Register'!$V:$V,B$3) | C12: =COUNTIFS('Feature Register'!$B:$B,$A12,'Feature Register'!$V:$V,C$3) | D12: =COUNTIFS('Feature Register'!$B:$B,$A12,'Feature Register'!$V:$V,D$3) | E12: =COUNTIFS('Feature Register'!$B:$B,$A12,'Feature Register'!$V:$V,E$3) | F12: =SUM(B12:E12) | G12: =SUMIF('Feature Register'!$B:$B,$A12,'Feature Register'!$T:$T)
A13: CRM | B13: =COUNTIFS('Feature Register'!$B:$B,$A13,'Feature Register'!$V:$V,B$3) | C13: =COUNTIFS('Feature Register'!$B:$B,$A13,'Feature Register'!$V:$V,C$3) | D13: =COUNTIFS('Feature Register'!$B:$B,$A13,'Feature Register'!$V:$V,D$3) | E13: =COUNTIFS('Feature Register'!$B:$B,$A13,'Feature Register'!$V:$V,E$3) | F13: =SUM(B13:E13) | G13: =SUMIF('Feature Register'!$B:$B,$A13,'Feature Register'!$T:$T)
A14: Human Resources | B14: =COUNTIFS('Feature Register'!$B:$B,$A14,'Feature Register'!$V:$V,B$3) | C14: =COUNTIFS('Feature Register'!$B:$B,$A14,'Feature Register'!$V:$V,C$3) | D14: =COUNTIFS('Feature Register'!$B:$B,$A14,'Feature Register'!$V:$V,D$3) | E14: =COUNTIFS('Feature Register'!$B:$B,$A14,'Feature Register'!$V:$V,E$3) | F14: =SUM(B14:E14) | G14: =SUMIF('Feature Register'!$B:$B,$A14,'Feature Register'!$T:$T)
A15: Service Center | B15: =COUNTIFS('Feature Register'!$B:$B,$A15,'Feature Register'!$V:$V,B$3) | C15: =COUNTIFS('Feature Register'!$B:$B,$A15,'Feature Register'!$V:$V,C$3) | D15: =COUNTIFS('Feature Register'!$B:$B,$A15,'Feature Register'!$V:$V,D$3) | E15: =COUNTIFS('Feature Register'!$B:$B,$A15,'Feature Register'!$V:$V,E$3) | F15: =SUM(B15:E15) | G15: =SUMIF('Feature Register'!$B:$B,$A15,'Feature Register'!$T:$T)
A16: Platform | B16: =COUNTIFS('Feature Register'!$B:$B,$A16,'Feature Register'!$V:$V,B$3) | C16: =COUNTIFS('Feature Register'!$B:$B,$A16,'Feature Register'!$V:$V,C$3) | D16: =COUNTIFS('Feature Register'!$B:$B,$A16,'Feature Register'!$V:$V,D$3) | E16: =COUNTIFS('Feature Register'!$B:$B,$A16,'Feature Register'!$V:$V,E$3) | F16: =SUM(B16:E16) | G16: =SUMIF('Feature Register'!$B:$B,$A16,'Feature Register'!$T:$T)
A17: TOTAL | B17: =SUM(B4:B16) | C17: =SUM(C4:C16) | D17: =SUM(D4:D16) | E17: =SUM(E4:E16) | F17: =SUM(F4:F16) | G17: =SUM(G4:G16)
A19: Build days = sum of the Effort (days) column, which is populated only on rows carrying a Recommended Action.
A20: Counts are live COUNTIFS against the register — they update when you re-classify a row.

Sheet Legend & Method
A1: Legend and method
A3: Column | B3: How it was derived | C3: Who fills it
A4: Component ID | B4: Assigned per L1 domain: FIN / ORD / PRC / INV / SHP / MFG / PRJ / CAT / PTY / CRM / HCM / SVC / SYS. | C4: Fixed
A5: L1 Domain, Module, Submodule | B5: Derived from the Application/ folder structure and the CQRS handler groupings. | C5: Fixed
A6: Function / Workflow | B6: One row per coherent business function, grouping the handlers that implement it. 265 rows cover 737 operation files. | C6: Fixed
A7: Artifact Type | B7: Screen / Report / API / Batch / Workflow / Mobile / Configuration — judged from the handler set and whether a client screen exists. | C7: Claude — review
A8: Arabic / RTL | B8: MEASURED per feature folder: share of .tsx files calling getTranslatedLabel. Compliant >=85%, Partial 40–85%, Non-Compliant <40%. Applied at module level, so individual screens may differ. | C8: Claude — verify per screen
A9: Priority | B9: Proposed, weighing business criticality against the size of the Odoo gap. | C9: YOU — this is a business call
A10: Sequence | B10: Running order within the L1 domain. Placeholder ordering only. | C10: YOU
A11: EGY / KSA Market applicability | B11: LEFT BLANK except for the three e-invoicing and tax-filing rows. Nothing in the code indicates market applicability. | C11: YOU
A12: Recommended Action | B12: Filled only where a concrete gap or defect was identified. | C12: Claude — review
A13: Status | B13: Completed = implemented and in use. Under Development = exists but with a known material gap. Planned = nothing built. | C13: YOU — reconcile with reality
A14: Owner, Target Release | B14: LEFT BLANK. Assignment and release planning are yours. | C14: YOU
... A22: Code Reference | B22: Path to the folder or file that implements it, so any row can be checked against the source. | C22: Fixed — verifiable
A24: Provenance
A25: Compiled 2026-08-23 from a direct inventory of the working tree, not from estimates or memory.
A26: 737 CQRS operation files across 68 module groups in Application/; 892 Domain entities; 146 API controllers.
A27: Frontend signals measured across 922 .ts/.tsx files in client-app/src.
A28: Odoo comparison is against Odoo 17/18 Community plus the standard Enterprise apps named in the Odoo Equivalent column.
A29: Structure follows the "Z ERP (1).xlsx" template: same first 20 columns and the same dropdown vocabularies, extended with four Odoo columns (U–X).
A30: Companion narrative: ERPv2/ERPv2-Brief.md.
